gtm_manager/__init__.py
gtm_manager/account.py
gtm_manager/base.py
gtm_manager/built_in_variable.py
gtm_manager/container.py
gtm_manager/exceptions.py
gtm_manager/folder.py
gtm_manager/manager.py
gtm_manager/parameter.py
gtm_manager/permission.py
gtm_manager/tag.py
gtm_manager/trigger.py
gtm_manager/utils.py
gtm_manager/utils_auth.py
gtm_manager/variable.py
gtm_manager/version.py
gtm_manager/workspace.py
gtm_manager-0.3.0.dist-info/LICENSE
gtm_manager-0.3.0.dist-info/METADATA
gtm_manager-0.3.0.dist-info/WHEEL
gtm_manager-0.3.0.dist-info/top_level.txt
gtm_manager-0.3.0.dist-info/RECORD
