Metadata-Version: 2.1
Name: gtm-manager
Version: 0.3.0
Summary: An object-oriented helper library wrapping the Tag Manager API Client Library for Python.
Home-page: UNKNOWN
Author: Trakken Web Services
Author-email: christian@trakken.de
License: UNKNOWN
Keywords: gtm,google tag manager
Platform: UNKNOWN
Classifier: Development Status :: 4 - Beta
Classifier: Programming Language :: Python :: 3.5
Classifier: Programming Language :: Python :: 3.6
Classifier: Programming Language :: Python :: 3.7
Classifier: License :: OSI Approved :: MIT License
Requires-Dist: google-auth-oauthlib
Requires-Dist: google-auth
Requires-Dist: google-api-python-client
Requires-Dist: retrying
Requires-Dist: ratelimit
Provides-Extra: docs
Requires-Dist: sphinx (>=1.8.2) ; extra == 'docs'
Requires-Dist: sphinx-rtd-theme ; extra == 'docs'
Provides-Extra: tests
Requires-Dist: pytest ; extra == 'tests'
